[
  {
    "code": "880201.SH",
    "name": "黑龙江"
  },
  {
    "code": "880202.SH",
    "name": "新疆板块"
  },
  {
    "code": "880203.SH",
    "name": "吉林板块"
  },
  {
    "code": "880204.SH",
    "name": "甘肃板块"
  },
  {
    "code": "880205.SH",
    "name": "辽宁板块"
  },
  {
    "code": "880206.SH",
    "name": "青海板块"
  },
  {
    "code": "880207.SH",
    "name": "北京板块"
  },
  {
    "code": "880208.SH",
    "name": "陕西板块"
  },
  {
    "code": "880209.SH",
    "name": "天津板块"
  },
  {
    "code": "880210.SH",
    "name": "广西板块"
  },
  {
    "code": "880211.SH",
    "name": "河北板块"
  },
  {
    "code": "880212.SH",
    "name": "广东板块"
  },
  {
    "code": "880213.SH",
    "name": "河南板块"
  },
  {
    "code": "880214.SH",
    "name": "宁夏板块"
  },
  {
    "code": "880215.SH",
    "name": "山东板块"
  },
  {
    "code": "880216.SH",
    "name": "上海板块"
  },
  {
    "code": "880217.SH",
    "name": "山西板块"
  },
  {
    "code": "880218.SH",
    "name": "深圳板块"
  },
  {
    "code": "880219.SH",
    "name": "湖北板块"
  },
  {
    "code": "880220.SH",
    "name": "福建板块"
  },
  {
    "code": "880221.SH",
    "name": "湖南板块"
  },
  {
    "code": "880222.SH",
    "name": "江西板块"
  },
  {
    "code": "880223.SH",
    "name": "四川板块"
  },
  {
    "code": "880224.SH",
    "name": "安徽板块"
  },
  {
    "code": "880225.SH",
    "name": "重庆板块"
  },
  {
    "code": "880226.SH",
    "name": "江苏板块"
  },
  {
    "code": "880227.SH",
    "name": "云南板块"
  },
  {
    "code": "880228.SH",
    "name": "浙江板块"
  },
  {
    "code": "880229.SH",
    "name": "贵州板块"
  },
  {
    "code": "880230.SH",
    "name": "海南板块"
  },
  {
    "code": "880231.SH",
    "name": "西藏板块"
  },
  {
    "code": "880232.SH",
    "name": "内蒙板块"
  }
]